mso_text_summarizer/__init__.py
mso_text_summarizer/text_summarizer.py
mso_text_summarizer-0.0.1.dist-info/METADATA
mso_text_summarizer-0.0.1.dist-info/WHEEL
mso_text_summarizer-0.0.1.dist-info/top_level.txt
mso_text_summarizer-0.0.1.dist-info/RECORD
